packagedraft/__init__.py
packagedraft/example.py
packagedraft-0.0.0.dist-info/METADATA
packagedraft-0.0.0.dist-info/WHEEL
packagedraft-0.0.0.dist-info/licenses/LICENSE
packagedraft-0.0.0.dist-info/RECORD
