Metadata-Version: 2.1
Name: packagedraft
Version: 0.0.0
Summary: A small example package
Author-email: Juan Lima <nkhklkstksch@icloud.com>
License-File: LICENSE
Classifier: License :: OSI Approved :: MIT License
Classifier: Operating System :: OS Independent
Classifier: Programming Language :: Python :: 3
Requires-Python: >=3.7
